verilog/memory.v
module memory (
	input wire clk,
	input wire write,
	input wire [15:0] addr,
	input wire [15:0] data_in,
	output reg [15:0] data_out
);

	reg [15:0] mem [0:65535];

	always @(posedge clk) begin
		if (write) mem[addr] <= data_in;

		data_out <= mem[addr];
	end

endmodule

verilog/tb_memory.v
`timescale 1ns/1ps

module tb_memory;
	reg clk;
	reg write;
	reg [15:0] addr;
	reg [15:0] data_in;
	wire [15:0] data_out;

	memory uut (
		.clk(clk),
		.write(write),
		.addr(addr),
		.data_in(data_in),
		.data_out(data_out)
	 );

	// clock generation (10ns period)
	always #5 clk = ~clk;

	task write_test(input [15:0] a, input [15:0] x);
	begin
		write = 1;
		addr = a;
		data_in = x;
		$display("[%h] <= %h", addr, data_in);
		@(posedge clk);
	end
	endtask

	task read_test(input [15:0] a);
	begin
		write = 0;
		addr = a;
		@(posedge clk);
		@(posedge clk);
		$display("[%h] => %h", addr, data_out);
	end
	endtask

	initial begin
		$readmemh("main.hex", uut.mem);
		$dumpfile("dump.vcd");
		$dumpvars(0, tb_memory);
	end

	integer i;

	initial begin
		clk = 0;

		for (i = 0; i < 50; i = i + 1) begin
			read_test(i);
		end

		write_test(16'h000A, 16'h1234);
		write_test(16'h000B, 16'hABCD);
		read_test(16'h000A);
		read_test(16'h000B);

		$finish;
	end
endmodule

verilog/dump.vcd
$date
	Sat Mar 28 10:03:08 2026
$end
$version
	Icarus Verilog
$end
$timescale
	1ps
$end
$scope module tb_memory $end
$var wire 16 ! data_out [15:0] $end
$var reg 16 " addr [15:0] $end
$var reg 1 # clk $end
$var reg 16 $ data_in [15:0] $end
$var reg 1 % write $end
$var integer 32 & i [31:0] $end
$scope module uut $end
$var wire 16 ' addr [15:0] $end
$var wire 1 # clk $end
$var wire 16 ( data_in [15:0] $end
$var wire 1 % write $end
$var reg 16 ) data_out [15:0] $end
$upscope $end
$scope task read_test $end
$var reg 16 * a [15:0] $end
$upscope $end
$scope task write_test $end
$var reg 16 + a [15:0] $end
$var reg 16 , x [15:0] $end
$upscope $end
$upscope $end
$enddefinitions $end
$comment Show the parameter values. $end
$dumpall
$end
#0
$dumpvars
bx ,
bx +
b0 *
bx )
bx (
b0 '
b0 &
0%
bx $
0#
b0 "
bx !
$end
#5000
b101101 !
b101101 )
1#
#10000
0#
#15000
b1 "
b1 '
b1 *
b1 &
1#
#20000
0#
#25000
1#
#30000
0#
#35000
b10 "
b10 '
b10 *
b10 &
1#
#40000
0#
#45000
b11 !
b11 )
1#
#50000
0#
#55000
b11 "
b11 '
b11 *
b11 &
1#
#60000
0#
#65000
b101010 !
b101010 )
1#
#70000
0#
#75000
b100 "
b100 '
b100 *
b100 &
1#
#80000
0#
#85000
1#
#90000
0#
#95000
b101 "
b101 '
b101 *
b101 &
1#
#100000
0#
#105000
b110 !
b110 )
1#
#110000
0#
#115000
b110 "
b110 '
b110 *
b110 &
1#
#120000
0#
#125000
b101100 !
b101100 )
1#
#130000
0#
#135000
b111 "
b111 '
b111 *
b111 &
1#
#140000
0#
#145000
b101010 !
b101010 )
1#
#150000
0#
#155000
b1000 "
b1000 '
b1000 *
b1000 &
1#
#160000
0#
#165000
b1001 !
b1001 )
1#
#170000
0#
#175000
b1001 "
b1001 '
b1001 *
b1001 &
1#
#180000
0#
#185000
b101011 !
b101011 )
1#
#190000
0#
#195000
b1010 "
b1010 '
b1010 *
b1010 &
1#
#200000
0#
#205000
b101010 !
b101010 )
1#
#210000
0#
#215000
b1011 "
b1011 '
b1011 *
b1011 &
1#
#220000
0#
#225000
b1100 !
b1100 )
1#
#230000
0#
#235000
b1100 "
b1100 '
b1100 *
b1100 &
1#
#240000
0#
#245000
b101010 !
b101010 )
1#
#250000
0#
#255000
b1101 "
b1101 '
b1101 *
b1101 &
1#
#260000
0#
#265000
b101101 !
b101101 )
1#
#270000
0#
#275000
b1110 "
b1110 '
b1110 *
b1110 &
1#
#280000
0#
#285000
b1111 !
b1111 )
1#
#290000
0#
#295000
b1111 "
b1111 '
b1111 *
b1111 &
1#
#300000
0#
#305000
b101011 !
b101011 )
1#
#310000
0#
#315000
b10000 "
b10000 '
b10000 *
b10000 &
1#
#320000
0#
#325000
1#
#330000
0#
#335000
b10001 "
b10001 '
b10001 *
b10001 &
1#
#340000
0#
#345000
b10010 !
b10010 )
1#
#350000
0#
#355000
b10010 "
b10010 '
b10010 *
b10010 &
1#
#360000
0#
#365000
b101010 !
b101010 )
1#
#370000
0#
#375000
b10011 "
b10011 '
b10011 *
b10011 &
1#
#380000
0#
#385000
1#
#390000
0#
#395000
b10100 "
b10100 '
b10100 *
b10100 &
1#
#400000
0#
#405000
b10101 !
b10101 )
1#
#410000
0#
#415000
b10101 "
b10101 '
b10101 *
b10101 &
1#
#420000
0#
#425000
b101100 !
b101100 )
1#
#430000
0#
#435000
b10110 "
b10110 '
b10110 *
b10110 &
1#
#440000
0#
#445000
b101010 !
b101010 )
1#
#450000
0#
#455000
b10111 "
b10111 '
b10111 *
b10111 &
1#
#460000
0#
#465000
b11000 !
b11000 )
1#
#470000
0#
#475000
b11000 "
b11000 '
b11000 *
b11000 &
1#
#480000
0#
#485000
b101010 !
b101010 )
1#
#490000
0#
#495000
b11001 "
b11001 '
b11001 *
b11001 &
1#
#500000
0#
#505000
b101011 !
b101011 )
1#
#510000
0#
#515000
b11010 "
b11010 '
b11010 *
b11010 &
1#
#520000
0#
#525000
b11011 !
b11011 )
1#
#530000
0#
#535000
b11011 "
b11011 '
b11011 *
b11011 &
1#
#540000
0#
#545000
b101100 !
b101100 )
1#
#550000
0#
#555000
b11100 "
b11100 '
b11100 *
b11100 &
1#
#560000
0#
#565000
1#
#570000
0#
#575000
b11101 "
b11101 '
b11101 *
b11101 &
1#
#580000
0#
#585000
b11110 !
b11110 )
1#
#590000
0#
#595000
b11110 "
b11110 '
b11110 *
b11110 &
1#
#600000
0#
#605000
b101010 !
b101010 )
1#
#610000
0#
#615000
b11111 "
b11111 '
b11111 *
b11111 &
1#
#620000
0#
#625000
1#
#630000
0#
#635000
b100000 "
b100000 '
b100000 *
b100000 &
1#
#640000
0#
#645000
b100001 !
b100001 )
1#
#650000
0#
#655000
b100001 "
b100001 '
b100001 *
b100001 &
1#
#660000
0#
#665000
b101101 !
b101101 )
1#
#670000
0#
#675000
b100010 "
b100010 '
b100010 *
b100010 &
1#
#680000
0#
#685000
b101010 !
b101010 )
1#
#690000
0#
#695000
b100011 "
b100011 '
b100011 *
b100011 &
1#
#700000
0#
#705000
b100100 !
b100100 )
1#
#710000
0#
#715000
b100100 "
b100100 '
b100100 *
b100100 &
1#
#720000
0#
#725000
b101010 !
b101010 )
1#
#730000
0#
#735000
b100101 "
b100101 '
b100101 *
b100101 &
1#
#740000
0#
#745000
b101100 !
b101100 )
1#
#750000
0#
#755000
b100110 "
b100110 '
b100110 *
b100110 &
1#
#760000
0#
#765000
b100111 !
b100111 )
1#
#770000
0#
#775000
b100111 "
b100111 '
b100111 *
b100111 &
1#
#780000
0#
#785000
b101110 !
b101110 )
1#
#790000
0#
#795000
b101000 "
b101000 '
b101000 *
b101000 &
1#
#800000
0#
#805000
1#
#810000
0#
#815000
b101001 "
b101001 '
b101001 *
b101001 &
1#
#820000
0#
#825000
b0 !
b0 )
1#
#830000
0#
#835000
b101010 "
b101010 '
b101010 *
b101010 &
1#
#840000
0#
#845000
1#
#850000
0#
#855000
b101011 "
b101011 '
b101011 *
b101011 &
1#
#860000
0#
#865000
1#
#870000
0#
#875000
b101100 "
b101100 '
b101100 *
b101100 &
1#
#880000
0#
#885000
b1 !
b1 )
1#
#890000
0#
#895000
b101101 "
b101101 '
b101101 *
b101101 &
1#
#900000
0#
#905000
b0 !
b0 )
1#
#910000
0#
#915000
b101110 "
b101110 '
b101110 *
b101110 &
1#
#920000
0#
#925000
1#
#930000
0#
#935000
b101111 "
b101111 '
b101111 *
b101111 &
1#
#940000
0#
#945000
bx !
bx )
1#
#950000
0#
#955000
b110000 "
b110000 '
b110000 *
b110000 &
1#
#960000
0#
#965000
1#
#970000
0#
#975000
b110001 "
b110001 '
b110001 *
b110001 &
1#
#980000
0#
#985000
1#
#990000
0#
#995000
b1001000110100 $
b1001000110100 (
b1010 "
b1010 '
1%
b1001000110100 ,
b1010 +
b110010 &
1#
#1000000
0#
#1005000
b101010 !
b101010 )
b1010101111001101 $
b1010101111001101 (
b1011 "
b1011 '
b1010101111001101 ,
b1011 +
1#
#1010000
0#
#1015000
b1100 !
b1100 )
b1010 "
b1010 '
0%
b1010 *
1#
#1020000
0#
#1025000
b1001000110100 !
b1001000110100 )
1#
#1030000
0#
#1035000
b1011 "
b1011 '
b1011 *
1#
#1040000
0#
#1045000
b1010101111001101 !
b1010101111001101 )
1#
