verilog/memory.v
module memory (
	input wire clock,
	input wire reset,
	input wire write_enable,
	input wire [15:0] data_in,
	output reg [15:0] data_out
);

	reg [15:0] mem [0:65535];
	reg [15:0] addr;
	reg phase; // 0 = expect address, 1 = expect data

	always @(negedge clock) begin
		if (reset) begin
			phase <= 0;
		end else if (write_enable) begin
			case (phase)
				0: begin
					addr <= data_in;
					phase <= 1;
				end
				1: begin
					mem[addr] <= data_in;
					phase <= 0;
				end
			endcase
		end else begin
			data_out <= mem[data_in];
		end
	end

endmodule

verilog/subleq_cpu.v
module subleq_cpu (
	input wire clock,
	input wire reset,
	input wire [15:0] data_in,
	output reg [15:0] data_out,
	output reg write_enable
);

reg [15:0] pc, regA, regB, regC, valA, valB;

reg [2:0] state;

always @(posedge clock) begin
	if (reset) begin
		pc <= 0;
		state <= 0;
	end else begin
		case (state)
			0: begin
				write_enable <= 0;
				data_out <= pc;
				state <= 1;
			end
			1: begin
				regA <= data_in;
				data_out <= pc + 1;
				state <= 2;
			end
			2: begin
				regB <= data_in;
				data_out <= pc + 2;
				state <= 3;
			end
			3: begin
				regC <= data_in;
				data_out <= regA;
				state <= 4;
			end
			4: begin
				valA <= data_in;
				data_out <= regB;
				state <= 5;
			end
			5: begin
				valB = data_in - valA;
				pc <= (valB <= 0) ? regC : pc + 3;
				write_enable <= 1;
				data_out <= regB;
				state <= 6;
			end
			6: begin
				data_out <= valB;
				state <= 0;
			end
		endcase
	end
end

endmodule

verilog/tb_subleq_cpu.v
module tb_subleq_cpu;
	reg clock = 1;
	reg reset = 1;

	wire [15:0] data_cpu_to_mem;
	wire [15:0] data_mem_to_cpu;
	wire write_enable;

	always #1 clock = ~clock;

	subleq_cpu cpu (
		.clock(clock),
		.reset(reset),
		.data_in(data_mem_to_cpu),
		.data_out(data_cpu_to_mem),
		.write_enable(write_enable)
	);

	memory mem (
		.clock(clock),
		.reset(reset),
		.data_in(data_cpu_to_mem),
		.data_out(data_mem_to_cpu),
		.write_enable(write_enable)
	);

	initial begin
		$readmemh("main.hex", mem.mem);
		$dumpfile("wave.vcd");
		$dumpvars(0, tb_subleq_cpu);

		#5 reset = 0;

		#5000 $finish;
	end

	always @(posedge clock) begin
/*
		$display("t=%0t | PC=%h | A=%h | B=%h | C=%h | [A]=%h | [B]=%h",
			$time,
			cpu.pc,
			cpu.regA,
			cpu.regB,
			cpu.regC,
			cpu.valA,
			cpu.valB
		);
		$display("t=%0t | WE=%b | CPU->MEM=%h | MEM->CPU=%h",
			$time,
			write_enable,
			data_cpu_to_mem,
			data_mem_to_cpu
		);
*/
	end

	integer cycle = 0;

	always @(posedge clock) begin
		cycle = cycle + 1;
		if (cycle == 6*16) begin
			$display("Fib: %0d", mem.mem[45]);
			cycle = 0;
		end
	end
endmodule

verilog/wave.vcd
$date
	Sat Mar 28 20:04:27 2026
$end
$version
	Icarus Verilog
$end
$timescale
	1s
$end
$scope module tb_subleq_cpu $end
$var wire 1 ! write_enable $end
$var wire 16 " data_mem_to_cpu [15:0] $end
$var wire 16 # data_cpu_to_mem [15:0] $end
$var reg 1 $ clock $end
$var reg 1 % reset $end
$var integer 32 & cycle [31:0] $end
$scope module cpu $end
$var wire 1 $ clock $end
$var wire 1 % reset $end
$var wire 16 ' data_in [15:0] $end
$var reg 16 ( data_out [15:0] $end
$var reg 16 ) pc [15:0] $end
$var reg 16 * regA [15:0] $end
$var reg 16 + regB [15:0] $end
$var reg 16 , regC [15:0] $end
$var reg 3 - state [2:0] $end
$var reg 16 . valA [15:0] $end
$var reg 16 / valB [15:0] $end
$var reg 1 ! write_enable $end
$upscope $end
$scope module mem $end
$var wire 1 $ clock $end
$var wire 16 0 data_in [15:0] $end
$var wire 1 % reset $end
$var wire 1 ! write_enable $end
$var reg 16 1 addr [15:0] $end
$var reg 16 2 data_out [15:0] $end
$var reg 1 3 phase $end
$upscope $end
$upscope $end
$enddefinitions $end
$comment Show the parameter values. $end
$dumpall
$end
#0
$dumpvars
x3
bx 2
bx 1
bx 0
bx /
bx .
b0 -
bx ,
bx +
bx *
b0 )
bx (
bx '
b0 &
1%
1$
bx #
bx "
x!
$end
#1
03
0$
#2
b1 &
1$
#3
0$
#4
b10 &
1$
#5
0$
0%
#6
b1 -
b0 #
b0 (
b0 0
0!
b11 &
1$
#7
b101101 "
b101101 '
b101101 2
0$
#8
b10 -
b1 #
b1 (
b1 0
b101101 *
b100 &
1$
#9
0$
#10
b11 -
b10 #
b10 (
b10 0
b101101 +
b101 &
1$
#11
b11 "
b11 '
b11 2
0$
#12
b100 -
b101101 #
b101101 (
b101101 0
b11 ,
b110 &
1$
#13
b0 "
b0 '
b0 2
0$
#14
b101 -
b0 .
b111 &
1$
#15
0$
#16
b110 -
1!
b11 )
b0 /
b1000 &
1$
#17
13
b101101 1
0$
#18
b0 -
b0 #
b0 (
b0 0
b1001 &
1$
#19
03
0$
#20
b1 -
b11 #
b11 (
b11 0
0!
b1010 &
1$
#21
b101010 "
b101010 '
b101010 2
0$
#22
b10 -
b100 #
b100 (
b100 0
b101010 *
b1011 &
1$
#23
0$
#24
b11 -
b101 #
b101 (
b101 0
b101010 +
b1100 &
1$
#25
b110 "
b110 '
b110 2
0$
#26
b100 -
b101010 #
b101010 (
b101010 0
b110 ,
b1101 &
1$
#27
b0 "
b0 '
b0 2
0$
#28
b101 -
b1110 &
1$
#29
0$
#30
b110 -
1!
b110 )
b1111 &
1$
#31
13
b101010 1
0$
#32
b0 -
b0 #
b0 (
b0 0
b10000 &
1$
#33
03
0$
#34
b1 -
b110 #
b110 (
b110 0
0!
b10001 &
1$
#35
b101100 "
b101100 '
b101100 2
0$
#36
b10 -
b111 #
b111 (
b111 0
b101100 *
b10010 &
1$
#37
b101010 "
b101010 '
b101010 2
0$
#38
b11 -
b1000 #
b1000 (
b1000 0
b10011 &
1$
#39
b1001 "
b1001 '
b1001 2
0$
#40
b100 -
b101100 #
b101100 (
b101100 0
b1001 ,
b10100 &
1$
#41
b1 "
b1 '
b1 2
0$
#42
b101 -
b101010 #
b101010 (
b101010 0
b1 .
b10101 &
1$
#43
b0 "
b0 '
b0 2
0$
#44
b110 -
1!
b1001 )
b1111111111111111 /
b10110 &
1$
#45
13
0$
#46
b0 -
b1111111111111111 #
b1111111111111111 (
b1111111111111111 0
b10111 &
1$
#47
03
0$
#48
b1 -
b1001 #
b1001 (
b1001 0
0!
b11000 &
1$
#49
b101011 "
b101011 '
b101011 2
0$
#50
b10 -
b1010 #
b1010 (
b1010 0
b101011 *
b11001 &
1$
#51
b101010 "
b101010 '
b101010 2
0$
#52
b11 -
b1011 #
b1011 (
b1011 0
b11010 &
1$
#53
b1100 "
b1100 '
b1100 2
0$
#54
b100 -
b101011 #
b101011 (
b101011 0
b1100 ,
b11011 &
1$
#55
b0 "
b0 '
b0 2
0$
#56
b101 -
b101010 #
b101010 (
b101010 0
b0 .
b11100 &
1$
#57
b1111111111111111 "
b1111111111111111 '
b1111111111111111 2
0$
#58
b110 -
1!
b1100 )
b11101 &
1$
#59
13
0$
#60
b0 -
b1111111111111111 #
b1111111111111111 (
b1111111111111111 0
b11110 &
1$
#61
03
0$
#62
b1 -
b1100 #
b1100 (
b1100 0
0!
b11111 &
1$
#63
b101010 "
b101010 '
b101010 2
0$
#64
b10 -
b1101 #
b1101 (
b1101 0
b101010 *
b100000 &
1$
#65
b101101 "
b101101 '
b101101 2
0$
#66
b11 -
b1110 #
b1110 (
b1110 0
b101101 +
b100001 &
1$
#67
b1111 "
b1111 '
b1111 2
0$
#68
b100 -
b101010 #
b101010 (
b101010 0
b1111 ,
b100010 &
1$
#69
b1111111111111111 "
b1111111111111111 '
b1111111111111111 2
0$
#70
b101 -
b101101 #
b101101 (
b101101 0
b1111111111111111 .
b100011 &
1$
#71
b0 "
b0 '
b0 2
0$
#72
b110 -
1!
b1111 )
b1 /
b100100 &
1$
#73
13
b101101 1
0$
#74
b0 -
b1 #
b1 (
b1 0
b100101 &
1$
#75
03
0$
#76
b1 -
b1111 #
b1111 (
b1111 0
0!
b100110 &
1$
#77
b101011 "
b101011 '
b101011 2
0$
#78
b10 -
b10000 #
b10000 (
b10000 0
b101011 *
b100111 &
1$
#79
0$
#80
b11 -
b10001 #
b10001 (
b10001 0
b101011 +
b101000 &
1$
#81
b10010 "
b10010 '
b10010 2
0$
#82
b100 -
b101011 #
b101011 (
b101011 0
b10010 ,
b101001 &
1$
#83
b0 "
b0 '
b0 2
0$
#84
b101 -
b0 .
b101010 &
1$
#85
0$
#86
b110 -
1!
b10010 )
b101011 &
b0 /
1$
#87
13
b101011 1
0$
#88
b0 -
b0 #
b0 (
b0 0
b101100 &
1$
#89
03
0$
#90
b1 -
b10010 #
b10010 (
b10010 0
0!
b101101 &
1$
#91
b101010 "
b101010 '
b101010 2
0$
#92
b10 -
b10011 #
b10011 (
b10011 0
b101010 *
b101110 &
1$
#93
0$
#94
b11 -
b10100 #
b10100 (
b10100 0
b101010 +
b101111 &
1$
#95
b10101 "
b10101 '
b10101 2
0$
#96
b100 -
b101010 #
b101010 (
b101010 0
b10101 ,
b110000 &
1$
#97
b1111111111111111 "
b1111111111111111 '
b1111111111111111 2
0$
#98
b101 -
b1111111111111111 .
b110001 &
1$
#99
0$
#100
b110 -
1!
b10101 )
b110010 &
1$
#101
13
b101010 1
0$
#102
b0 -
b0 #
b0 (
b0 0
b110011 &
1$
#103
03
0$
#104
b1 -
b10101 #
b10101 (
b10101 0
0!
b110100 &
1$
#105
b101100 "
b101100 '
b101100 2
0$
#106
b10 -
b10110 #
b10110 (
b10110 0
b101100 *
b110101 &
1$
#107
b101010 "
b101010 '
b101010 2
0$
#108
b11 -
b10111 #
b10111 (
b10111 0
b110110 &
1$
#109
b11000 "
b11000 '
b11000 2
0$
#110
b100 -
b101100 #
b101100 (
b101100 0
b11000 ,
b110111 &
1$
#111
b1 "
b1 '
b1 2
0$
#112
b101 -
b101010 #
b101010 (
b101010 0
b1 .
b111000 &
1$
#113
b0 "
b0 '
b0 2
0$
#114
b110 -
1!
b11000 )
b111001 &
b1111111111111111 /
1$
#115
13
0$
#116
b0 -
b1111111111111111 #
b1111111111111111 (
b1111111111111111 0
b111010 &
1$
#117
03
0$
#118
b1 -
b11000 #
b11000 (
b11000 0
0!
b111011 &
1$
#119
b101010 "
b101010 '
b101010 2
0$
#120
b10 -
b11001 #
b11001 (
b11001 0
b101010 *
b111100 &
1$
#121
b101011 "
b101011 '
b101011 2
0$
#122
b11 -
b11010 #
b11010 (
b11010 0
b101011 +
b111101 &
1$
#123
b11011 "
b11011 '
b11011 2
0$
#124
b100 -
b101010 #
b101010 (
b101010 0
b11011 ,
b111110 &
1$
#125
b1111111111111111 "
b1111111111111111 '
b1111111111111111 2
0$
#126
b101 -
b101011 #
b101011 (
b101011 0
b1111111111111111 .
b111111 &
1$
#127
b0 "
b0 '
b0 2
0$
#128
b110 -
1!
b11011 )
b1 /
b1000000 &
1$
#129
13
b101011 1
0$
#130
b0 -
b1 #
b1 (
b1 0
b1000001 &
1$
#131
03
0$
#132
b1 -
b11011 #
b11011 (
b11011 0
0!
b1000010 &
1$
#133
b101100 "
b101100 '
b101100 2
0$
#134
b10 -
b11100 #
b11100 (
b11100 0
b101100 *
b1000011 &
1$
#135
0$
#136
b11 -
b11101 #
b11101 (
b11101 0
b101100 +
b1000100 &
1$
#137
b11110 "
b11110 '
b11110 2
0$
#138
b100 -
b101100 #
b101100 (
b101100 0
b11110 ,
b1000101 &
1$
#139
b1 "
b1 '
b1 2
0$
#140
b101 -
b1 .
b1000110 &
1$
#141
0$
#142
b110 -
1!
b11110 )
b1000111 &
b0 /
1$
#143
13
b101100 1
0$
#144
b0 -
b0 #
b0 (
b0 0
b1001000 &
1$
#145
03
0$
#146
b1 -
b11110 #
b11110 (
b11110 0
0!
b1001001 &
1$
#147
b101010 "
b101010 '
b101010 2
0$
#148
b10 -
b11111 #
b11111 (
b11111 0
b101010 *
b1001010 &
1$
#149
0$
#150
b11 -
b100000 #
b100000 (
b100000 0
b101010 +
b1001011 &
1$
#151
b100001 "
b100001 '
b100001 2
0$
#152
b100 -
b101010 #
b101010 (
b101010 0
b100001 ,
b1001100 &
1$
#153
b1111111111111111 "
b1111111111111111 '
b1111111111111111 2
0$
#154
b101 -
b1111111111111111 .
b1001101 &
1$
#155
0$
#156
b110 -
1!
b100001 )
b1001110 &
1$
#157
13
b101010 1
0$
#158
b0 -
b0 #
b0 (
b0 0
b1001111 &
1$
#159
03
0$
#160
b1 -
b100001 #
b100001 (
b100001 0
0!
b1010000 &
1$
#161
b101101 "
b101101 '
b101101 2
0$
#162
b10 -
b100010 #
b100010 (
b100010 0
b101101 *
b1010001 &
1$
#163
b101010 "
b101010 '
b101010 2
0$
#164
b11 -
b100011 #
b100011 (
b100011 0
b1010010 &
1$
#165
b100100 "
b100100 '
b100100 2
0$
#166
b100 -
b101101 #
b101101 (
b101101 0
b100100 ,
b1010011 &
1$
#167
b1 "
b1 '
b1 2
0$
#168
b101 -
b101010 #
b101010 (
b101010 0
b1 .
b1010100 &
1$
#169
b0 "
b0 '
b0 2
0$
#170
b110 -
1!
b100100 )
b1010101 &
b1111111111111111 /
1$
#171
13
0$
#172
b0 -
b1111111111111111 #
b1111111111111111 (
b1111111111111111 0
b1010110 &
1$
#173
03
0$
#174
b1 -
b100100 #
b100100 (
b100100 0
0!
b1010111 &
1$
#175
b101010 "
b101010 '
b101010 2
0$
#176
b10 -
b100101 #
b100101 (
b100101 0
b101010 *
b1011000 &
1$
#177
b101100 "
b101100 '
b101100 2
0$
#178
b11 -
b100110 #
b100110 (
b100110 0
b101100 +
b1011001 &
1$
#179
b100111 "
b100111 '
b100111 2
0$
#180
b100 -
b101010 #
b101010 (
b101010 0
b100111 ,
b1011010 &
1$
#181
b1111111111111111 "
b1111111111111111 '
b1111111111111111 2
0$
#182
b101 -
b101100 #
b101100 (
b101100 0
b1111111111111111 .
b1011011 &
1$
#183
b0 "
b0 '
b0 2
0$
#184
b110 -
1!
b100111 )
b1 /
b1011100 &
1$
#185
13
b101100 1
0$
#186
b0 -
b1 #
b1 (
b1 0
b1011101 &
1$
#187
03
0$
#188
b1 -
b100111 #
b100111 (
b100111 0
0!
b1011110 &
1$
#189
b101110 "
b101110 '
b101110 2
0$
#190
b10 -
b101000 #
b101000 (
b101000 0
b101110 *
b1011111 &
1$
#191
0$
#192
b11 -
b101001 #
b101001 (
b101001 0
b101110 +
b0 &
1$
#193
b0 "
b0 '
b0 2
0$
#194
b100 -
b101110 #
b101110 (
b101110 0
b0 ,
b1 &
1$
#195
0$
#196
b101 -
b0 .
b10 &
1$
#197
0$
#198
b110 -
1!
b0 )
b11 &
b0 /
1$
#199
13
b101110 1
0$
#200
b0 -
b0 #
b0 (
b0 0
b100 &
1$
#201
03
0$
#202
b1 -
0!
b101 &
1$
#203
b101101 "
b101101 '
b101101 2
0$
#204
b10 -
b1 #
b1 (
b1 0
b101101 *
b110 &
1$
#205
0$
#206
b11 -
b10 #
b10 (
b10 0
b101101 +
b111 &
1$
#207
b11 "
b11 '
b11 2
0$
#208
b100 -
b101101 #
b101101 (
b101101 0
b11 ,
b1000 &
1$
#209
b1 "
b1 '
b1 2
0$
#210
b101 -
b1 .
b1001 &
1$
#211
0$
#212
b110 -
1!
b11 )
b1010 &
1$
#213
13
b101101 1
0$
#214
b0 -
b0 #
b0 (
b0 0
b1011 &
1$
#215
03
0$
#216
b1 -
b11 #
b11 (
b11 0
0!
b1100 &
1$
#217
b101010 "
b101010 '
b101010 2
0$
#218
b10 -
b100 #
b100 (
b100 0
b101010 *
b1101 &
1$
#219
0$
#220
b11 -
b101 #
b101 (
b101 0
b101010 +
b1110 &
1$
#221
b110 "
b110 '
b110 2
0$
#222
b100 -
b101010 #
b101010 (
b101010 0
b110 ,
b1111 &
1$
#223
b1111111111111111 "
b1111111111111111 '
b1111111111111111 2
0$
#224
b101 -
b1111111111111111 .
b10000 &
1$
#225
0$
#226
b110 -
1!
b110 )
b10001 &
1$
#227
13
b101010 1
0$
#228
b0 -
b0 #
b0 (
b0 0
b10010 &
1$
#229
03
0$
#230
b1 -
b110 #
b110 (
b110 0
0!
b10011 &
1$
#231
b101100 "
b101100 '
b101100 2
0$
#232
b10 -
b111 #
b111 (
b111 0
b101100 *
b10100 &
1$
#233
b101010 "
b101010 '
b101010 2
0$
#234
b11 -
b1000 #
b1000 (
b1000 0
b10101 &
1$
#235
b1001 "
b1001 '
b1001 2
0$
#236
b100 -
b101100 #
b101100 (
b101100 0
b1001 ,
b10110 &
1$
#237
b1 "
b1 '
b1 2
0$
#238
b101 -
b101010 #
b101010 (
b101010 0
b1 .
b10111 &
1$
#239
b0 "
b0 '
b0 2
0$
#240
b110 -
1!
b1001 )
b1111111111111111 /
b11000 &
1$
#241
13
0$
#242
b0 -
b1111111111111111 #
b1111111111111111 (
b1111111111111111 0
b11001 &
1$
#243
03
0$
#244
b1 -
b1001 #
b1001 (
b1001 0
0!
b11010 &
1$
#245
b101011 "
b101011 '
b101011 2
0$
#246
b10 -
b1010 #
b1010 (
b1010 0
b101011 *
b11011 &
1$
#247
b101010 "
b101010 '
b101010 2
0$
#248
b11 -
b1011 #
b1011 (
b1011 0
b11100 &
1$
#249
b1100 "
b1100 '
b1100 2
0$
#250
b100 -
b101011 #
b101011 (
b101011 0
b1100 ,
b11101 &
1$
#251
b1 "
b1 '
b1 2
0$
#252
b101 -
b101010 #
b101010 (
b101010 0
b11110 &
1$
#253
b1111111111111111 "
b1111111111111111 '
b1111111111111111 2
0$
#254
b110 -
1!
b1100 )
b11111 &
b1111111111111110 /
1$
#255
13
0$
#256
b0 -
b1111111111111110 #
b1111111111111110 (
b1111111111111110 0
b100000 &
1$
#257
03
0$
#258
b1 -
b1100 #
b1100 (
b1100 0
0!
b100001 &
1$
#259
b101010 "
b101010 '
b101010 2
0$
#260
b10 -
b1101 #
b1101 (
b1101 0
b101010 *
b100010 &
1$
#261
b101101 "
b101101 '
b101101 2
0$
#262
b11 -
b1110 #
b1110 (
b1110 0
b101101 +
b100011 &
1$
#263
b1111 "
b1111 '
b1111 2
0$
#264
b100 -
b101010 #
b101010 (
b101010 0
b1111 ,
b100100 &
1$
#265
b1111111111111110 "
b1111111111111110 '
b1111111111111110 2
0$
#266
b101 -
b101101 #
b101101 (
b101101 0
b1111111111111110 .
b100101 &
1$
#267
b0 "
b0 '
b0 2
0$
#268
b110 -
1!
b1111 )
b10 /
b100110 &
1$
#269
13
b101101 1
0$
#270
b0 -
b10 #
b10 (
b10 0
b100111 &
1$
#271
03
0$
#272
b1 -
b1111 #
b1111 (
b1111 0
0!
b101000 &
1$
#273
b101011 "
b101011 '
b101011 2
0$
#274
b10 -
b10000 #
b10000 (
b10000 0
b101011 *
b101001 &
1$
#275
0$
#276
b11 -
b10001 #
b10001 (
b10001 0
b101011 +
b101010 &
1$
#277
b10010 "
b10010 '
b10010 2
0$
#278
b100 -
b101011 #
b101011 (
b101011 0
b10010 ,
b101011 &
1$
#279
b1 "
b1 '
b1 2
0$
#280
b101 -
b1 .
b101100 &
1$
#281
0$
#282
b110 -
1!
b10010 )
b101101 &
b0 /
1$
#283
13
b101011 1
0$
#284
b0 -
b0 #
b0 (
b0 0
b101110 &
1$
#285
03
0$
#286
b1 -
b10010 #
b10010 (
b10010 0
0!
b101111 &
1$
#287
b101010 "
b101010 '
b101010 2
0$
#288
b10 -
b10011 #
b10011 (
b10011 0
b101010 *
b110000 &
1$
#289
0$
#290
b11 -
b10100 #
b10100 (
b10100 0
b101010 +
b110001 &
1$
#291
b10101 "
b10101 '
b10101 2
0$
#292
b100 -
b101010 #
b101010 (
b101010 0
b10101 ,
b110010 &
1$
#293
b1111111111111110 "
b1111111111111110 '
b1111111111111110 2
0$
#294
b101 -
b1111111111111110 .
b110011 &
1$
#295
0$
#296
b110 -
1!
b10101 )
b110100 &
1$
#297
13
b101010 1
0$
#298
b0 -
b0 #
b0 (
b0 0
b110101 &
1$
#299
03
0$
#300
b1 -
b10101 #
b10101 (
b10101 0
0!
b110110 &
1$
#301
b101100 "
b101100 '
b101100 2
0$
#302
b10 -
b10110 #
b10110 (
b10110 0
b101100 *
b110111 &
1$
#303
b101010 "
b101010 '
b101010 2
0$
#304
b11 -
b10111 #
b10111 (
b10111 0
b111000 &
1$
#305
b11000 "
b11000 '
b11000 2
0$
#306
b100 -
b101100 #
b101100 (
b101100 0
b11000 ,
b111001 &
1$
#307
b1 "
b1 '
b1 2
0$
#308
b101 -
b101010 #
b101010 (
b101010 0
b1 .
b111010 &
1$
#309
b0 "
b0 '
b0 2
0$
#310
b110 -
1!
b11000 )
b111011 &
b1111111111111111 /
1$
#311
13
0$
#312
b0 -
b1111111111111111 #
b1111111111111111 (
b1111111111111111 0
b111100 &
1$
#313
03
0$
#314
b1 -
b11000 #
b11000 (
b11000 0
0!
b111101 &
1$
#315
b101010 "
b101010 '
b101010 2
0$
#316
b10 -
b11001 #
b11001 (
b11001 0
b101010 *
b111110 &
1$
#317
b101011 "
b101011 '
b101011 2
0$
#318
b11 -
b11010 #
b11010 (
b11010 0
b101011 +
b111111 &
1$
#319
b11011 "
b11011 '
b11011 2
0$
#320
b100 -
b101010 #
b101010 (
b101010 0
b11011 ,
b1000000 &
1$
#321
b1111111111111111 "
b1111111111111111 '
b1111111111111111 2
0$
#322
b101 -
b101011 #
b101011 (
b101011 0
b1111111111111111 .
b1000001 &
1$
#323
b0 "
b0 '
b0 2
0$
#324
b110 -
1!
b11011 )
b1 /
b1000010 &
1$
#325
13
b101011 1
0$
#326
b0 -
b1 #
b1 (
b1 0
b1000011 &
1$
#327
03
0$
#328
b1 -
b11011 #
b11011 (
b11011 0
0!
b1000100 &
1$
#329
b101100 "
b101100 '
b101100 2
0$
#330
b10 -
b11100 #
b11100 (
b11100 0
b101100 *
b1000101 &
1$
#331
0$
#332
b11 -
b11101 #
b11101 (
b11101 0
b101100 +
b1000110 &
1$
#333
b11110 "
b11110 '
b11110 2
0$
#334
b100 -
b101100 #
b101100 (
b101100 0
b11110 ,
b1000111 &
1$
#335
b1 "
b1 '
b1 2
0$
#336
b101 -
b1 .
b1001000 &
1$
#337
0$
#338
b110 -
1!
b11110 )
b1001001 &
b0 /
1$
#339
13
b101100 1
0$
#340
b0 -
b0 #
b0 (
b0 0
b1001010 &
1$
#341
03
0$
#342
b1 -
b11110 #
b11110 (
b11110 0
0!
b1001011 &
1$
#343
b101010 "
b101010 '
b101010 2
0$
#344
b10 -
b11111 #
b11111 (
b11111 0
b101010 *
b1001100 &
1$
#345
0$
#346
b11 -
b100000 #
b100000 (
b100000 0
b101010 +
b1001101 &
1$
#347
b100001 "
b100001 '
b100001 2
0$
#348
b100 -
b101010 #
b101010 (
b101010 0
b100001 ,
b1001110 &
1$
#349
b1111111111111111 "
b1111111111111111 '
b1111111111111111 2
0$
#350
b101 -
b1111111111111111 .
b1001111 &
1$
#351
0$
#352
b110 -
1!
b100001 )
b1010000 &
1$
#353
13
b101010 1
0$
#354
b0 -
b0 #
b0 (
b0 0
b1010001 &
1$
#355
03
0$
#356
b1 -
b100001 #
b100001 (
b100001 0
0!
b1010010 &
1$
#357
b101101 "
b101101 '
b101101 2
0$
#358
b10 -
b100010 #
b100010 (
b100010 0
b101101 *
b1010011 &
1$
#359
b101010 "
b101010 '
b101010 2
0$
#360
b11 -
b100011 #
b100011 (
b100011 0
b1010100 &
1$
#361
b100100 "
b100100 '
b100100 2
0$
#362
b100 -
b101101 #
b101101 (
b101101 0
b100100 ,
b1010101 &
1$
#363
b10 "
b10 '
b10 2
0$
#364
b101 -
b101010 #
b101010 (
b101010 0
b10 .
b1010110 &
1$
#365
b0 "
b0 '
b0 2
0$
#366
b110 -
1!
b100100 )
b1010111 &
b1111111111111110 /
1$
#367
13
0$
#368
b0 -
b1111111111111110 #
b1111111111111110 (
b1111111111111110 0
b1011000 &
1$
#369
03
0$
#370
b1 -
b100100 #
b100100 (
b100100 0
0!
b1011001 &
1$
#371
b101010 "
b101010 '
b101010 2
0$
#372
b10 -
b100101 #
b100101 (
b100101 0
b101010 *
b1011010 &
1$
#373
b101100 "
b101100 '
b101100 2
0$
#374
b11 -
b100110 #
b100110 (
b100110 0
b101100 +
b1011011 &
1$
#375
b100111 "
b100111 '
b100111 2
0$
#376
b100 -
b101010 #
b101010 (
b101010 0
b100111 ,
b1011100 &
1$
#377
b1111111111111110 "
b1111111111111110 '
b1111111111111110 2
0$
#378
b101 -
b101100 #
b101100 (
b101100 0
b1111111111111110 .
b1011101 &
1$
#379
b0 "
b0 '
b0 2
0$
#380
b110 -
1!
b100111 )
b10 /
b1011110 &
1$
#381
13
b101100 1
0$
#382
b0 -
b10 #
b10 (
b10 0
b1011111 &
1$
#383
03
0$
#384
b1 -
b100111 #
b100111 (
b100111 0
0!
b0 &
1$
#385
b101110 "
b101110 '
b101110 2
0$
#386
b10 -
b101000 #
b101000 (
b101000 0
b101110 *
b1 &
1$
#387
0$
#388
b11 -
b101001 #
b101001 (
b101001 0
b101110 +
b10 &
1$
#389
b0 "
b0 '
b0 2
0$
#390
b100 -
b101110 #
b101110 (
b101110 0
b0 ,
b11 &
1$
#391
0$
#392
b101 -
b0 .
b100 &
1$
#393
0$
#394
b110 -
1!
b0 )
b101 &
b0 /
1$
#395
13
b101110 1
0$
#396
b0 -
b0 #
b0 (
b0 0
b110 &
1$
#397
03
0$
#398
b1 -
0!
b111 &
1$
#399
b101101 "
b101101 '
b101101 2
0$
#400
b10 -
b1 #
b1 (
b1 0
b101101 *
b1000 &
1$
#401
0$
#402
b11 -
b10 #
b10 (
b10 0
b101101 +
b1001 &
1$
#403
b11 "
b11 '
b11 2
0$
#404
b100 -
b101101 #
b101101 (
b101101 0
b11 ,
b1010 &
1$
#405
b10 "
b10 '
b10 2
0$
#406
b101 -
b10 .
b1011 &
1$
#407
0$
#408
b110 -
1!
b11 )
b1100 &
1$
#409
13
b101101 1
0$
#410
b0 -
b0 #
b0 (
b0 0
b1101 &
1$
#411
03
0$
#412
b1 -
b11 #
b11 (
b11 0
0!
b1110 &
1$
#413
b101010 "
b101010 '
b101010 2
0$
#414
b10 -
b100 #
b100 (
b100 0
b101010 *
b1111 &
1$
#415
0$
#416
b11 -
b101 #
b101 (
b101 0
b101010 +
b10000 &
1$
#417
b110 "
b110 '
b110 2
0$
#418
b100 -
b101010 #
b101010 (
b101010 0
b110 ,
b10001 &
1$
#419
b1111111111111110 "
b1111111111111110 '
b1111111111111110 2
0$
#420
b101 -
b1111111111111110 .
b10010 &
1$
#421
0$
#422
b110 -
1!
b110 )
b10011 &
1$
#423
13
b101010 1
0$
#424
b0 -
b0 #
b0 (
b0 0
b10100 &
1$
#425
03
0$
#426
b1 -
b110 #
b110 (
b110 0
0!
b10101 &
1$
#427
b101100 "
b101100 '
b101100 2
0$
#428
b10 -
b111 #
b111 (
b111 0
b101100 *
b10110 &
1$
#429
b101010 "
b101010 '
b101010 2
0$
#430
b11 -
b1000 #
b1000 (
b1000 0
b10111 &
1$
#431
b1001 "
b1001 '
b1001 2
0$
#432
b100 -
b101100 #
b101100 (
b101100 0
b1001 ,
b11000 &
1$
#433
b10 "
b10 '
b10 2
0$
#434
b101 -
b101010 #
b101010 (
b101010 0
b10 .
b11001 &
1$
#435
b0 "
b0 '
b0 2
0$
#436
b110 -
1!
b1001 )
b1111111111111110 /
b11010 &
1$
#437
13
0$
#438
b0 -
b1111111111111110 #
b1111111111111110 (
b1111111111111110 0
b11011 &
1$
#439
03
0$
#440
b1 -
b1001 #
b1001 (
b1001 0
0!
b11100 &
1$
#441
b101011 "
b101011 '
b101011 2
0$
#442
b10 -
b1010 #
b1010 (
b1010 0
b101011 *
b11101 &
1$
#443
b101010 "
b101010 '
b101010 2
0$
#444
b11 -
b1011 #
b1011 (
b1011 0
b11110 &
1$
#445
b1100 "
b1100 '
b1100 2
0$
#446
b100 -
b101011 #
b101011 (
b101011 0
b1100 ,
b11111 &
1$
#447
b1 "
b1 '
b1 2
0$
#448
b101 -
b101010 #
b101010 (
b101010 0
b1 .
b100000 &
1$
#449
b1111111111111110 "
b1111111111111110 '
b1111111111111110 2
0$
#450
b110 -
1!
b1100 )
b100001 &
b1111111111111101 /
1$
#451
13
0$
#452
b0 -
b1111111111111101 #
b1111111111111101 (
b1111111111111101 0
b100010 &
1$
#453
03
0$
#454
b1 -
b1100 #
b1100 (
b1100 0
0!
b100011 &
1$
#455
b101010 "
b101010 '
b101010 2
0$
#456
b10 -
b1101 #
b1101 (
b1101 0
b101010 *
b100100 &
1$
#457
b101101 "
b101101 '
b101101 2
0$
#458
b11 -
b1110 #
b1110 (
b1110 0
b101101 +
b100101 &
1$
#459
b1111 "
b1111 '
b1111 2
0$
#460
b100 -
b101010 #
b101010 (
b101010 0
b1111 ,
b100110 &
1$
#461
b1111111111111101 "
b1111111111111101 '
b1111111111111101 2
0$
#462
b101 -
b101101 #
b101101 (
b101101 0
b1111111111111101 .
b100111 &
1$
#463
b0 "
b0 '
b0 2
0$
#464
b110 -
1!
b1111 )
b11 /
b101000 &
1$
#465
13
b101101 1
0$
#466
b0 -
b11 #
b11 (
b11 0
b101001 &
1$
#467
03
0$
#468
b1 -
b1111 #
b1111 (
b1111 0
0!
b101010 &
1$
#469
b101011 "
b101011 '
b101011 2
0$
#470
b10 -
b10000 #
b10000 (
b10000 0
b101011 *
b101011 &
1$
#471
0$
#472
b11 -
b10001 #
b10001 (
b10001 0
b101011 +
b101100 &
1$
#473
b10010 "
b10010 '
b10010 2
0$
#474
b100 -
b101011 #
b101011 (
b101011 0
b10010 ,
b101101 &
1$
#475
b1 "
b1 '
b1 2
0$
