project/tt_memory.v
module tt_memory (
	input wire clock,
	input wire reset,
	input wire read_latch,
	input wire write_latch,
	input wire [7:0] data_in,
	output reg [7:0] data_out
);

	reg [15:0] memory [0:65535];
	reg [15:0] address;
	reg [7:0] lsb;
	reg [1:0] read_state, write_state;

	always @(posedge clock) begin
		if (reset) begin
			$display("Reset mode active!");
			read_state <= 0;
			write_state <= 0;
		end else begin
			if (read_latch) begin
				address[7:0] <= data_in;
				read_state <= 1;
			end

			else if (read_state) begin
				case (read_state)
					1: begin
						address[15:8] <= data_in;
						read_state <= 2;
					end
					2: begin
						data_out <= memory[address][7:0];
						read_state <= 3;
					end
					3: begin
						data_out <= memory[address][15:8];
						read_state <= 0;
					end
				endcase
			end

			else if (write_latch) begin
				address[7:0] <= data_in;
				write_state <= 1;
			end

			else if (write_state) begin
				case (write_state)
					1: begin
						address[15:8] <= data_in;
						write_state <= 2;
					end
					2: begin
						lsb <= data_in;
						write_state <= 3;
					end
					3: begin
						memory[address] <= {data_in, lsb};
						write_state <= 0;
					end
				endcase
			end
		end
	end

endmodule

tt/tt_subleq_cpu.v
module tt_okforth_subleq_cpu (
	input  wire [7:0] ui_in,	// Dedicated inputs
	output wire [7:0] uo_out,	// Dedicated outputs
	input  wire [7:0] uio_in,	// IOs: Input path
	output wire [7:0] uio_out,	// IOs: Output path
	output wire [7:0] uio_oe,	// IOs: Enable path (active high: 0=input, 1=output)
	input  wire       ena,		// will go high when the design is enabled
	input  wire       clk,		// clock
	input  wire       rst_n		// reset_n - low to reset
);

	wire clock;
	wire reset;
wire [7:0] data_in; reg [7:0] data_out;
	reg read_latch;
	reg write_latch;

	assign clock = clk;
	assign reset = ~rst_n;
	assign data_in = ui_in;
	assign uo_out = data_out;

	assign uio_oe = 8'hFF;			// set all uio pins as output
	assign uio_out[0] = read_latch;
	assign uio_out[1] = write_latch;
	assign uio_out[2] = clock;
	assign uio_out[3] = reset;

	reg [15:0] pc, regA, regB, regC, valA, valB, diff;

	reg [4:0] state;

	always @(posedge clock) begin
		if (reset) begin
			pc <= 0;
			state <= 0;
			read_latch <= 0;
			write_latch <= 0;
		end else begin
			case (state)
				0: begin
					read_latch <= 1;
					data_out <= pc[7:0];
					state <= 1;
				end
				1: begin
					read_latch <= 0;
					data_out <= pc[15:8];
					state <= 2;
				end
				2: begin
					pc <= pc + 1;
					state <= 3;
				end
				3: begin
					state <= 4;
				end
				4: begin
					regA[7:0] <= data_in;
					state <= 5;
				end
				5: begin
					regA[15:8] <= data_in;

					read_latch <= 1;
					data_out <= pc[7:0];
					state <= 6;
				end
				6: begin
					read_latch <= 0;
					data_out <= pc[15:8];
					state <= 7;
				end
				7: begin
					pc <= pc + 1;
					state <= 8;
				end
				8: begin
					state <= 9;
				end
				9: begin
					regB[7:0] <= data_in;
					state <= 10;
				end
				10: begin
					regB[15:8] <= data_in;

					read_latch <= 1;
					data_out <= pc[7:0];
					state <= 11;
				end
				11: begin
					read_latch <= 0;
					data_out <= pc[15:8];
					state <= 12;
				end
				12: begin
					pc <= pc + 1;
					state <= 13;
				end
				13: begin
					state <= 14;
				end
				14: begin
					regC[7:0] <= data_in;
					state <= 15;
				end
				15: begin
					regC[15:8] <= data_in;

					read_latch <= 1;
					data_out <= regA[7:0];
					state <= 16;
				end
				16: begin
					read_latch <= 0;
					data_out <= regA[15:8];
					state <= 17;
				end
				17: begin
					state <= 18;
				end
				18: begin
					state <= 19;
				end
				19: begin
					valA[7:0] <= data_in;
					state <= 20;
				end
				20: begin
					valA[15:8] <= data_in;

					read_latch <= 1;
					data_out <= regB[7:0];
					state <= 21;
				end
				21: begin
					read_latch <= 0;
					data_out <= regB[15:8];
					state <= 22;
				end
				22: begin
					state <= 23;
				end
				23: begin
					state <= 24;
				end
				24: begin
					valB[7:0] <= data_in;
					state <= 25;
				end
				25: begin
					valB[15:8] <= data_in;

					write_latch <= 1;
					data_out <= regB[7:0];
					state <= 26;
				end
				26: begin
					diff <= valB - valA;

					write_latch <= 0;
					data_out <= regB[15:8];
					state <= 27;
				end
				27: begin
					pc <= (diff <= 0) ? regC : pc;

					data_out <= diff[7:0];
					state <= 28;
				end
				28: begin
					data_out <= diff[15:8];
					state <= 0;
				end
			endcase
		end
	end

endmodule

tt/tb_tt_subleq_cpu.v
module tb_tt_okforth_subleq;
	reg clock;
	reg reset;
	
	wire [7:0] data_cpu_to_mem, data_mem_to_cpu, signals;
	wire read_latch, write_latch;

	assign read_latch = signals[0];
	assign write_latch = signals[1];
	assign clock_signal = signals[2];
	assign reset_signal = signals[3];
	
	always #1 clock = ~clock;

	tt_okforth_subleq_cpu cpu (
		.clk(clock),
		.rst_n(reset),
		.ui_in(data_mem_to_cpu),
		.uo_out(data_cpu_to_mem),
		.uio_out(signals)
	);

	tt_memory mem (
		.clock(clock_signal),
		.reset(reset_signal),
		.read_latch(read_latch),
		.write_latch(write_latch),
		.data_in(data_cpu_to_mem),
		.data_out(data_mem_to_cpu)
	);

	initial begin
		$readmemh("main.hex", mem.memory);
		$dumpfile("dump.vcd");
		$dumpvars(0, tb_tt_okforth_subleq);

		clock = 1;
		reset = 0;

		#4;
		reset = 1;

		#10000 $finish;
	end

	always @(posedge clock) begin
		$display("t=%0t | PC=%h | A=%h | B=%h | C=%h | [A]=%h | [B]=%h | diff=%h",
			$time,
			cpu.pc,
			cpu.regA,
			cpu.regB,
			cpu.regC,
			cpu.valA,
			cpu.valB,
			cpu.diff
		);
		$display("t=%0t | RL=%b | WL=%b | CPU->MEM=%h | MEM->CPU=%h",
			$time,
			read_latch,
			write_latch,
			data_cpu_to_mem,
			data_mem_to_cpu
		);
		$display("fib: %d\n", mem.memory[44]);
	end
endmodule

project/dump.vcd
$date
	Sun Mar 29 18:25:30 2026
$end
$version
	Icarus Verilog
$end
$timescale
	1s
$end
$scope module tb_tt_okforth_subleq $end
$var wire 1 ! write_latch $end
$var wire 8 " signals [7:0] $end
$var wire 1 # reset_signal $end
$var wire 1 $ read_latch $end
$var wire 8 % data_mem_to_cpu [7:0] $end
$var wire 8 & data_cpu_to_mem [7:0] $end
$var wire 1 ' clock_signal $end
$var reg 1 ( clock $end
$var reg 1 ) reset $end
$scope module cpu $end
$var wire 1 ( clk $end
$var wire 1 * clock $end
$var wire 8 + data_in [7:0] $end
$var wire 1 , ena $end
$var wire 1 - reset $end
$var wire 1 ) rst_n $end
$var wire 8 . uio_in [7:0] $end
$var wire 8 / uio_oe [7:0] $end
$var wire 8 0 uo_out [7:0] $end
$var wire 8 1 uio_out [7:0] $end
$var wire 8 2 ui_in [7:0] $end
$var reg 8 3 data_out [7:0] $end
$var reg 16 4 diff [15:0] $end
$var reg 16 5 pc [15:0] $end
$var reg 1 6 read_latch $end
$var reg 16 7 regA [15:0] $end
$var reg 16 8 regB [15:0] $end
$var reg 16 9 regC [15:0] $end
$var reg 5 : state [4:0] $end
$var reg 16 ; valA [15:0] $end
$var reg 16 < valB [15:0] $end
$var reg 1 = write_latch $end
$upscope $end
$scope module mem $end
$var wire 1 ' clock $end
$var wire 8 > data_in [7:0] $end
$var wire 1 $ read_latch $end
$var wire 1 # reset $end
$var wire 1 ! write_latch $end
$var reg 16 ? address [15:0] $end
$var reg 8 @ data_out [7:0] $end
$var reg 8 A lsb [7:0] $end
$var reg 2 B read_state [1:0] $end
$var reg 2 C write_state [1:0] $end
$upscope $end
$upscope $end
$enddefinitions $end
$comment Show the parameter values. $end
$dumpall
$end
#0
$dumpvars
bx C
bx B
bx A
bx @
bx ?
bx >
x=
bx <
bx ;
bx :
bx 9
bx 8
bx 7
x6
bx 5
bx 4
bx 3
bx 2
bz11xx 1
bx 0
b11111111 /
bz .
1-
z,
bx +
1*
0)
1(
1'
bx &
bx %
x$
1#
bz11xx "
x!
$end
#1
0'
bz10xx "
bz10xx 1
0*
0(
#2
0!
0$
b0 C
b0 B
0=
06
b0 :
b0 5
1'
bz1100 "
bz1100 1
1*
1(
#3
0'
bz1000 "
bz1000 1
0*
0(
#4
1$
b1 :
b0 &
b0 0
b0 >
b0 3
16
0#
1'
0-
bz0101 "
bz0101 1
1*
1(
1)
#5
0'
bz0001 "
bz0001 1
0*
0(
#6
0$
b1 B
bx00000000 ?
b10 :
b1 5
06
1'
bz0100 "
bz0100 1
1*
1(
#7
0'
bz0000 "
bz0000 1
0*
0(
#8
b10 B
b0 ?
b11 :
1'
bz0100 "
bz0100 1
1*
1(
#9
0'
bz0000 "
bz0000 1
0*
0(
#10
b11 B
b101101 +
b101101 %
b101101 2
b101101 @
b100 :
1'
bz0100 "
bz0100 1
1*
1(
#11
0'
bz0000 "
bz0000 1
0*
0(
#12
b0 B
b0 +
b0 %
b0 2
b0 @
b101 :
bx00101101 7
1'
bz0100 "
bz0100 1
1*
1(
#13
0'
bz0000 "
bz0000 1
0*
0(
#14
1$
b110 :
b1 &
b1 0
b1 >
b1 3
16
b101101 7
1'
bz0101 "
bz0101 1
1*
1(
#15
0'
bz0001 "
bz0001 1
0*
0(
#16
0$
b1 B
b1 ?
b111 :
b10 5
b0 &
b0 0
b0 >
b0 3
06
1'
bz0100 "
bz0100 1
1*
1(
#17
0'
bz0000 "
bz0000 1
0*
0(
#18
b10 B
b1000 :
1'
bz0100 "
bz0100 1
1*
1(
#19
0'
bz0000 "
bz0000 1
0*
0(
#20
b11 B
b101101 +
b101101 %
b101101 2
b101101 @
b1001 :
1'
bz0100 "
bz0100 1
1*
1(
#21
0'
bz0000 "
bz0000 1
0*
0(
#22
b0 B
b0 +
b0 %
b0 2
b0 @
b1010 :
bx00101101 8
1'
bz0100 "
bz0100 1
1*
1(
#23
0'
bz0000 "
bz0000 1
0*
0(
#24
1$
b1011 :
b10 &
b10 0
b10 >
b10 3
16
b101101 8
1'
bz0101 "
bz0101 1
1*
1(
#25
0'
bz0001 "
bz0001 1
0*
0(
#26
0$
b1 B
b10 ?
b1100 :
b11 5
b0 &
b0 0
b0 >
b0 3
06
1'
bz0100 "
bz0100 1
1*
1(
#27
0'
bz0000 "
bz0000 1
0*
0(
#28
b10 B
b1101 :
1'
bz0100 "
bz0100 1
1*
1(
#29
0'
bz0000 "
bz0000 1
0*
0(
#30
b11 B
b11 +
b11 %
b11 2
b11 @
b1110 :
1'
bz0100 "
bz0100 1
1*
1(
#31
0'
bz0000 "
bz0000 1
0*
0(
#32
b0 B
b0 +
b0 %
b0 2
b0 @
b1111 :
bx00000011 9
1'
bz0100 "
bz0100 1
1*
1(
#33
0'
bz0000 "
bz0000 1
0*
0(
#34
1$
b10000 :
b101101 &
b101101 0
b101101 >
b101101 3
16
b11 9
1'
bz0101 "
bz0101 1
1*
1(
#35
0'
bz0001 "
bz0001 1
0*
0(
#36
0$
b1 B
b101101 ?
b10001 :
b0 &
b0 0
b0 >
b0 3
06
1'
bz0100 "
bz0100 1
1*
1(
#37
0'
bz0000 "
bz0000 1
0*
0(
#38
b10 B
b10010 :
1'
bz0100 "
bz0100 1
1*
1(
#39
0'
bz0000 "
bz0000 1
0*
0(
#40
b11 B
b10011 :
1'
bz0100 "
bz0100 1
1*
1(
#41
0'
bz0000 "
bz0000 1
0*
0(
#42
b0 B
b10100 :
bx00000000 ;
1'
bz0100 "
bz0100 1
1*
1(
#43
0'
bz0000 "
bz0000 1
0*
0(
#44
1$
b10101 :
b101101 &
b101101 0
b101101 >
b101101 3
16
b0 ;
1'
bz0101 "
bz0101 1
1*
1(
#45
0'
bz0001 "
bz0001 1
0*
0(
#46
0$
b1 B
b10110 :
b0 &
b0 0
b0 >
b0 3
06
1'
bz0100 "
bz0100 1
1*
1(
#47
0'
bz0000 "
bz0000 1
0*
0(
#48
b10 B
b10111 :
1'
bz0100 "
bz0100 1
1*
1(
#49
0'
bz0000 "
bz0000 1
0*
0(
#50
b11 B
b11000 :
1'
bz0100 "
bz0100 1
1*
1(
#51
0'
bz0000 "
bz0000 1
0*
0(
#52
b0 B
b11001 :
bx00000000 <
1'
bz0100 "
bz0100 1
1*
1(
#53
0'
bz0000 "
bz0000 1
0*
0(
#54
1!
b11010 :
b101101 &
b101101 0
b101101 >
b101101 3
1=
b0 <
1'
bz0110 "
bz0110 1
1*
1(
#55
0'
bz0010 "
bz0010 1
0*
0(
#56
0!
b1 C
b11011 :
b0 &
b0 0
b0 >
b0 3
0=
b0 4
1'
bz0100 "
bz0100 1
1*
1(
#57
0'
bz0000 "
bz0000 1
0*
0(
#58
b10 C
b11100 :
1'
bz0100 "
bz0100 1
1*
1(
#59
0'
bz0000 "
bz0000 1
0*
0(
#60
b11 C
b0 A
b0 :
1'
bz0100 "
bz0100 1
1*
1(
#61
0'
bz0000 "
bz0000 1
0*
0(
#62
1$
b0 C
b1 :
b11 &
b11 0
b11 >
b11 3
16
1'
bz0101 "
bz0101 1
1*
1(
#63
0'
bz0001 "
bz0001 1
0*
0(
#64
0$
b1 B
b11 ?
b10 :
b100 5
b0 &
b0 0
b0 >
b0 3
06
1'
bz0100 "
bz0100 1
1*
1(
#65
0'
bz0000 "
bz0000 1
0*
0(
#66
b10 B
b11 :
1'
bz0100 "
bz0100 1
1*
1(
#67
0'
bz0000 "
bz0000 1
0*
0(
#68
b11 B
b101010 +
b101010 %
b101010 2
b101010 @
b100 :
1'
bz0100 "
bz0100 1
1*
1(
#69
0'
bz0000 "
bz0000 1
0*
0(
#70
b0 B
b0 +
b0 %
b0 2
b0 @
b101 :
b101010 7
1'
bz0100 "
bz0100 1
1*
1(
#71
0'
bz0000 "
bz0000 1
0*
0(
#72
1$
b110 :
b100 &
b100 0
b100 >
b100 3
16
1'
bz0101 "
bz0101 1
1*
1(
#73
0'
bz0001 "
bz0001 1
0*
0(
#74
0$
b1 B
b100 ?
b111 :
b101 5
b0 &
b0 0
b0 >
b0 3
06
1'
bz0100 "
bz0100 1
1*
1(
#75
0'
bz0000 "
bz0000 1
0*
0(
#76
b10 B
b1000 :
1'
bz0100 "
bz0100 1
1*
1(
#77
0'
bz0000 "
bz0000 1
0*
0(
#78
b11 B
b101010 +
b101010 %
b101010 2
b101010 @
b1001 :
1'
bz0100 "
bz0100 1
1*
1(
#79
0'
bz0000 "
bz0000 1
0*
0(
#80
b0 B
b0 +
b0 %
b0 2
b0 @
b1010 :
b101010 8
1'
bz0100 "
bz0100 1
1*
1(
#81
0'
bz0000 "
bz0000 1
0*
0(
#82
1$
b1011 :
b101 &
b101 0
b101 >
b101 3
16
1'
bz0101 "
bz0101 1
1*
1(
#83
0'
bz0001 "
bz0001 1
0*
0(
#84
0$
b1 B
b101 ?
b1100 :
b110 5
b0 &
b0 0
b0 >
b0 3
06
1'
bz0100 "
bz0100 1
1*
1(
#85
0'
bz0000 "
bz0000 1
0*
0(
#86
b10 B
b1101 :
1'
bz0100 "
bz0100 1
1*
1(
#87
0'
bz0000 "
bz0000 1
0*
0(
#88
b11 B
b110 +
b110 %
b110 2
b110 @
b1110 :
1'
bz0100 "
bz0100 1
1*
1(
#89
0'
bz0000 "
bz0000 1
0*
0(
#90
b0 B
b0 +
b0 %
b0 2
b0 @
b1111 :
b110 9
1'
bz0100 "
bz0100 1
1*
1(
#91
0'
bz0000 "
bz0000 1
0*
0(
#92
1$
b10000 :
b101010 &
b101010 0
b101010 >
b101010 3
16
1'
bz0101 "
bz0101 1
1*
1(
#93
0'
bz0001 "
bz0001 1
0*
0(
#94
0$
b1 B
b101010 ?
b10001 :
b0 &
b0 0
b0 >
b0 3
06
1'
bz0100 "
bz0100 1
1*
1(
#95
0'
bz0000 "
bz0000 1
0*
0(
#96
b10 B
b10010 :
1'
bz0100 "
bz0100 1
1*
1(
#97
0'
bz0000 "
bz0000 1
0*
0(
#98
b11 B
b10011 :
1'
bz0100 "
bz0100 1
1*
1(
#99
0'
bz0000 "
bz0000 1
0*
0(
#100
b0 B
b10100 :
1'
bz0100 "
bz0100 1
1*
1(
#101
0'
bz0000 "
bz0000 1
0*
0(
#102
1$
b10101 :
b101010 &
b101010 0
b101010 >
b101010 3
16
1'
bz0101 "
bz0101 1
1*
1(
#103
0'
bz0001 "
bz0001 1
0*
0(
#104
0$
b1 B
b10110 :
b0 &
b0 0
b0 >
b0 3
06
1'
bz0100 "
bz0100 1
1*
1(
#105
0'
bz0000 "
bz0000 1
0*
0(
#106
b10 B
b10111 :
1'
bz0100 "
bz0100 1
1*
1(
#107
0'
bz0000 "
bz0000 1
0*
0(
#108
b11 B
b11000 :
1'
bz0100 "
bz0100 1
1*
1(
#109
0'
bz0000 "
bz0000 1
0*
0(
#110
b0 B
b11001 :
1'
bz0100 "
bz0100 1
1*
1(
#111
0'
bz0000 "
bz0000 1
0*
0(
#112
1!
b11010 :
b101010 &
b101010 0
b101010 >
b101010 3
1=
1'
bz0110 "
bz0110 1
1*
1(
#113
0'
bz0010 "
bz0010 1
0*
0(
#114
0!
b1 C
b11011 :
b0 &
b0 0
b0 >
b0 3
0=
1'
bz0100 "
bz0100 1
1*
1(
#115
0'
bz0000 "
bz0000 1
0*
0(
#116
b10 C
b11100 :
1'
bz0100 "
bz0100 1
1*
1(
#117
0'
bz0000 "
bz0000 1
0*
0(
#118
b11 C
b0 :
1'
bz0100 "
bz0100 1
1*
1(
#119
0'
bz0000 "
bz0000 1
0*
0(
#120
1$
b0 C
b1 :
b110 &
b110 0
b110 >
b110 3
16
1'
bz0101 "
bz0101 1
1*
1(
#121
0'
bz0001 "
bz0001 1
0*
0(
#122
0$
b1 B
b110 ?
b10 :
b111 5
b0 &
b0 0
b0 >
b0 3
06
1'
bz0100 "
bz0100 1
1*
1(
#123
0'
bz0000 "
bz0000 1
0*
0(
#124
b10 B
b11 :
1'
bz0100 "
bz0100 1
1*
1(
#125
0'
bz0000 "
bz0000 1
0*
0(
#126
b11 B
b101100 +
b101100 %
b101100 2
b101100 @
b100 :
1'
bz0100 "
bz0100 1
1*
1(
#127
0'
bz0000 "
bz0000 1
0*
0(
#128
b0 B
b0 +
b0 %
b0 2
b0 @
b101 :
b101100 7
1'
bz0100 "
bz0100 1
1*
1(
#129
0'
bz0000 "
bz0000 1
0*
0(
#130
1$
b110 :
b111 &
b111 0
b111 >
b111 3
16
1'
bz0101 "
bz0101 1
1*
1(
#131
0'
bz0001 "
bz0001 1
0*
0(
#132
0$
b1 B
b111 ?
b111 :
b1000 5
b0 &
b0 0
b0 >
b0 3
06
1'
bz0100 "
bz0100 1
1*
1(
#133
0'
bz0000 "
bz0000 1
0*
0(
#134
b10 B
b1000 :
1'
bz0100 "
bz0100 1
1*
1(
#135
0'
bz0000 "
bz0000 1
0*
0(
#136
b11 B
b101010 +
b101010 %
b101010 2
b101010 @
b1001 :
1'
bz0100 "
bz0100 1
1*
1(
#137
0'
bz0000 "
bz0000 1
0*
0(
#138
b0 B
b0 +
b0 %
b0 2
b0 @
b1010 :
1'
bz0100 "
bz0100 1
1*
1(
#139
0'
bz0000 "
bz0000 1
0*
0(
#140
1$
b1011 :
b1000 &
b1000 0
b1000 >
b1000 3
16
1'
bz0101 "
bz0101 1
1*
1(
#141
0'
bz0001 "
bz0001 1
0*
0(
#142
0$
b1 B
b1000 ?
b1100 :
b1001 5
b0 &
b0 0
b0 >
b0 3
06
1'
bz0100 "
bz0100 1
1*
1(
#143
0'
bz0000 "
bz0000 1
0*
0(
#144
b10 B
b1101 :
1'
bz0100 "
bz0100 1
1*
1(
#145
0'
bz0000 "
bz0000 1
0*
0(
#146
b11 B
b1001 +
b1001 %
b1001 2
b1001 @
b1110 :
1'
bz0100 "
bz0100 1
1*
1(
#147
0'
bz0000 "
bz0000 1
0*
0(
#148
b0 B
b0 +
b0 %
b0 2
b0 @
b1111 :
b1001 9
1'
bz0100 "
bz0100 1
1*
1(
#149
0'
bz0000 "
bz0000 1
0*
0(
#150
1$
b10000 :
b101100 &
b101100 0
b101100 >
b101100 3
16
1'
bz0101 "
bz0101 1
1*
1(
#151
0'
bz0001 "
bz0001 1
0*
0(
#152
0$
b1 B
b101100 ?
b10001 :
b0 &
b0 0
b0 >
b0 3
06
1'
bz0100 "
bz0100 1
1*
1(
#153
0'
bz0000 "
bz0000 1
0*
0(
#154
b10 B
b10010 :
1'
bz0100 "
bz0100 1
1*
1(
#155
0'
bz0000 "
bz0000 1
0*
0(
#156
b11 B
b1 +
b1 %
b1 2
b1 @
b10011 :
1'
bz0100 "
bz0100 1
1*
1(
#157
0'
bz0000 "
bz0000 1
0*
0(
#158
b0 B
b0 +
b0 %
b0 2
b0 @
b10100 :
b1 ;
1'
bz0100 "
bz0100 1
1*
1(
#159
0'
bz0000 "
bz0000 1
0*
0(
#160
1$
b10101 :
b101010 &
b101010 0
b101010 >
b101010 3
16
1'
bz0101 "
bz0101 1
1*
1(
#161
0'
bz0001 "
bz0001 1
0*
0(
#162
0$
b1 B
b101010 ?
b10110 :
b0 &
b0 0
b0 >
b0 3
06
1'
bz0100 "
bz0100 1
1*
1(
#163
0'
bz0000 "
bz0000 1
0*
0(
#164
b10 B
b10111 :
1'
bz0100 "
bz0100 1
1*
1(
#165
0'
bz0000 "
bz0000 1
0*
0(
#166
b11 B
b11000 :
1'
bz0100 "
bz0100 1
1*
1(
#167
0'
bz0000 "
bz0000 1
0*
0(
#168
b0 B
b11001 :
1'
bz0100 "
bz0100 1
1*
1(
#169
0'
bz0000 "
bz0000 1
0*
0(
#170
1!
b11010 :
b101010 &
b101010 0
b101010 >
b101010 3
1=
1'
bz0110 "
bz0110 1
1*
1(
#171
0'
bz0010 "
bz0010 1
0*
0(
#172
0!
b1 C
b11011 :
b0 &
b0 0
b0 >
b0 3
0=
b1111111111111111 4
1'
bz0100 "
bz0100 1
1*
1(
#173
0'
bz0000 "
bz0000 1
0*
0(
#174
b10 C
b11100 :
b11111111 &
b11111111 0
b11111111 >
b11111111 3
1'
bz0100 "
bz0100 1
1*
1(
#175
0'
bz0000 "
bz0000 1
0*
0(
#176
b11 C
b11111111 A
b0 :
1'
bz0100 "
bz0100 1
1*
1(
#177
0'
bz0000 "
bz0000 1
0*
0(
#178
1$
b0 C
b1 :
b1001 &
b1001 0
b1001 >
b1001 3
16
1'
bz0101 "
bz0101 1
1*
1(
#179
0'
bz0001 "
bz0001 1
0*
0(
#180
0$
b1 B
b1001 ?
b10 :
b1010 5
b0 &
b0 0
b0 >
b0 3
06
1'
bz0100 "
bz0100 1
1*
1(
#181
0'
bz0000 "
bz0000 1
0*
0(
#182
b10 B
b11 :
1'
bz0100 "
bz0100 1
1*
1(
#183
0'
bz0000 "
bz0000 1
0*
0(
#184
b11 B
b101011 +
b101011 %
b101011 2
b101011 @
b100 :
1'
bz0100 "
bz0100 1
1*
1(
#185
0'
bz0000 "
bz0000 1
0*
0(
#186
b0 B
b0 +
b0 %
b0 2
b0 @
b101 :
b101011 7
1'
bz0100 "
bz0100 1
1*
1(
#187
0'
bz0000 "
bz0000 1
0*
0(
#188
1$
b110 :
b1010 &
b1010 0
b1010 >
b1010 3
16
1'
bz0101 "
bz0101 1
1*
1(
#189
0'
bz0001 "
bz0001 1
0*
0(
#190
0$
b1 B
b1010 ?
b111 :
b1011 5
b0 &
b0 0
b0 >
b0 3
06
1'
bz0100 "
bz0100 1
1*
1(
#191
0'
bz0000 "
bz0000 1
0*
0(
#192
b10 B
b1000 :
1'
bz0100 "
bz0100 1
1*
1(
#193
0'
bz0000 "
bz0000 1
0*
0(
#194
b11 B
b101010 +
b101010 %
b101010 2
b101010 @
b1001 :
1'
bz0100 "
bz0100 1
1*
1(
#195
0'
bz0000 "
bz0000 1
0*
0(
#196
b0 B
b0 +
b0 %
b0 2
b0 @
b1010 :
1'
bz0100 "
bz0100 1
1*
1(
#197
0'
bz0000 "
bz0000 1
0*
0(
#198
1$
b1011 :
b1011 &
b1011 0
b1011 >
b1011 3
16
1'
bz0101 "
bz0101 1
1*
1(
#199
0'
bz0001 "
bz0001 1
0*
0(
#200
0$
b1 B
b1011 ?
b1100 :
b1100 5
b0 &
b0 0
b0 >
b0 3
06
1'
bz0100 "
bz0100 1
1*
1(
#201
0'
bz0000 "
bz0000 1
0*
0(
#202
b10 B
b1101 :
1'
bz0100 "
bz0100 1
1*
1(
#203
0'
bz0000 "
bz0000 1
0*
0(
#204
b11 B
b1100 +
b1100 %
b1100 2
b1100 @
b1110 :
1'
bz0100 "
bz0100 1
1*
1(
#205
0'
bz0000 "
bz0000 1
0*
0(
#206
b0 B
b0 +
b0 %
b0 2
b0 @
b1111 :
b1100 9
1'
bz0100 "
bz0100 1
1*
1(
#207
0'
bz0000 "
bz0000 1
0*
0(
#208
1$
b10000 :
b101011 &
b101011 0
b101011 >
b101011 3
16
1'
bz0101 "
bz0101 1
1*
1(
#209
0'
bz0001 "
bz0001 1
0*
0(
#210
0$
b1 B
b101011 ?
b10001 :
b0 &
b0 0
b0 >
b0 3
06
1'
bz0100 "
bz0100 1
1*
1(
#211
0'
bz0000 "
bz0000 1
0*
0(
#212
b10 B
b10010 :
1'
bz0100 "
bz0100 1
1*
1(
#213
0'
bz0000 "
bz0000 1
0*
0(
#214
b11 B
b10011 :
1'
bz0100 "
bz0100 1
1*
1(
#215
0'
bz0000 "
bz0000 1
0*
0(
#216
b0 B
b10100 :
b0 ;
1'
bz0100 "
bz0100 1
1*
1(
#217
0'
bz0000 "
bz0000 1
0*
0(
#218
1$
b10101 :
b101010 &
b101010 0
b101010 >
b101010 3
16
1'
bz0101 "
bz0101 1
1*
1(
#219
0'
bz0001 "
bz0001 1
0*
0(
#220
0$
b1 B
b101010 ?
b10110 :
b0 &
b0 0
b0 >
b0 3
06
1'
bz0100 "
bz0100 1
1*
1(
#221
0'
bz0000 "
bz0000 1
0*
0(
#222
b10 B
b10111 :
1'
bz0100 "
bz0100 1
1*
1(
#223
0'
bz0000 "
bz0000 1
0*
0(
#224
b11 B
b11111111 +
b11111111 %
b11111111 2
b11111111 @
b11000 :
1'
bz0100 "
bz0100 1
1*
1(
#225
0'
bz0000 "
bz0000 1
0*
0(
#226
b0 B
b11001 :
b11111111 <
1'
bz0100 "
bz0100 1
1*
1(
#227
0'
bz0000 "
bz0000 1
0*
0(
#228
1!
b11010 :
b101010 &
b101010 0
b101010 >
b101010 3
1=
b1111111111111111 <
1'
bz0110 "
bz0110 1
1*
1(
#229
0'
bz0010 "
bz0010 1
0*
0(
#230
0!
b1 C
b11011 :
b0 &
b0 0
b0 >
b0 3
0=
1'
bz0100 "
bz0100 1
1*
1(
#231
0'
bz0000 "
bz0000 1
0*
0(
#232
b10 C
b11100 :
b11111111 &
b11111111 0
b11111111 >
b11111111 3
1'
bz0100 "
bz0100 1
1*
1(
#233
0'
bz0000 "
bz0000 1
0*
0(
#234
b11 C
b0 :
1'
bz0100 "
bz0100 1
1*
1(
#235
0'
bz0000 "
bz0000 1
0*
0(
#236
1$
b0 C
b1 :
b1100 &
b1100 0
b1100 >
b1100 3
16
1'
bz0101 "
bz0101 1
1*
1(
#237
0'
bz0001 "
bz0001 1
0*
0(
#238
0$
b1 B
b1100 ?
b10 :
b1101 5
b0 &
b0 0
b0 >
b0 3
06
1'
bz0100 "
bz0100 1
1*
1(
#239
0'
bz0000 "
bz0000 1
0*
0(
#240
b10 B
b11 :
1'
bz0100 "
bz0100 1
1*
1(
#241
0'
bz0000 "
bz0000 1
0*
0(
#242
b11 B
b101010 +
b101010 %
b101010 2
b101010 @
b100 :
1'
bz0100 "
bz0100 1
1*
1(
#243
0'
bz0000 "
bz0000 1
0*
0(
#244
b0 B
b0 +
b0 %
b0 2
b0 @
b101 :
b101010 7
1'
bz0100 "
bz0100 1
1*
1(
#245
0'
bz0000 "
bz0000 1
0*
0(
#246
1$
b110 :
b1101 &
b1101 0
b1101 >
b1101 3
16
1'
bz0101 "
bz0101 1
1*
1(
#247
0'
bz0001 "
bz0001 1
0*
0(
#248
0$
b1 B
b1101 ?
b111 :
b1110 5
b0 &
b0 0
b0 >
b0 3
06
1'
bz0100 "
bz0100 1
1*
1(
#249
0'
bz0000 "
bz0000 1
0*
0(
#250
b10 B
b1000 :
1'
bz0100 "
bz0100 1
1*
1(
#251
0'
bz0000 "
bz0000 1
0*
0(
#252
b11 B
b101101 +
b101101 %
b101101 2
b101101 @
b1001 :
1'
bz0100 "
bz0100 1
1*
1(
#253
0'
bz0000 "
bz0000 1
0*
0(
#254
b0 B
b0 +
b0 %
b0 2
b0 @
b1010 :
b101101 8
1'
bz0100 "
bz0100 1
1*
1(
#255
0'
bz0000 "
bz0000 1
0*
0(
#256
1$
b1011 :
b1110 &
b1110 0
b1110 >
b1110 3
16
1'
bz0101 "
bz0101 1
1*
1(
#257
0'
bz0001 "
bz0001 1
0*
0(
#258
0$
b1 B
b1110 ?
b1100 :
b1111 5
b0 &
b0 0
b0 >
b0 3
06
1'
bz0100 "
bz0100 1
1*
1(
#259
0'
bz0000 "
bz0000 1
0*
0(
#260
b10 B
b1101 :
1'
bz0100 "
bz0100 1
1*
1(
#261
0'
bz0000 "
bz0000 1
0*
0(
#262
b11 B
b1111 +
b1111 %
b1111 2
b1111 @
b1110 :
1'
bz0100 "
bz0100 1
1*
1(
#263
0'
bz0000 "
bz0000 1
0*
0(
#264
b0 B
b0 +
b0 %
b0 2
b0 @
b1111 :
b1111 9
1'
bz0100 "
bz0100 1
1*
1(
#265
0'
bz0000 "
bz0000 1
0*
0(
#266
1$
b10000 :
b101010 &
b101010 0
b101010 >
b101010 3
16
1'
bz0101 "
bz0101 1
1*
1(
#267
0'
bz0001 "
bz0001 1
0*
0(
#268
0$
b1 B
b101010 ?
b10001 :
b0 &
b0 0
b0 >
b0 3
06
1'
bz0100 "
bz0100 1
1*
1(
#269
0'
bz0000 "
bz0000 1
0*
0(
#270
b10 B
b10010 :
1'
bz0100 "
bz0100 1
1*
1(
#271
0'
bz0000 "
bz0000 1
0*
0(
